cordstrap/__init__.py
cordstrap/__main__.py
cordstrap/channel.py
cordstrap/discord.py
cordstrap/template.py
cordstrap-0.1.1.dist-info/METADATA
cordstrap-0.1.1.dist-info/WHEEL
cordstrap-0.1.1.dist-info/entry_points.txt
cordstrap-0.1.1.dist-info/top_level.txt
cordstrap-0.1.1.dist-info/RECORD
