Metadata-Version: 2.1
Name: cordstrap
Version: 0.1.1
Summary: Bootstrap your Discord servers
Author-email: interrrp <int@addictedto.coffee>
License: MIT
Project-URL: homepage, https://github.com/interrrp/cordstrap
Project-URL: repository, https://github.com/interrrp/cordstrap
Requires-Python: ==3.12.*
Requires-Dist: typer[all] >=0.9.0
Requires-Dist: pydantic >=2.5.2
Requires-Dist: pydantic-yaml >=1.2.0
Requires-Dist: requests >=2.31.0
